{
  "match": "Argentina vs Algeria",
  "capture": "20260617T003453Z-argentina-vs-algeria",
  "n_goals": 7,
  "goals_source": "results",
  "reference": {
    "label": "Argentina",
    "venue": "polymarket"
  },
  "n_detected": 3,
  "n_trades": 3,
  "trades": [
    {
      "t_ms": 1781658451326,
      "jump": 0.08,
      "pre": 0.625,
      "p_entry": 0.665,
      "p_exit": 0.645,
      "reverted_pp": 2.0,
      "pnl_pp": 1.5,
      "surprise": 0.128,
      "gain_prior": 0.625,
      "surprising": false
    },
    {
      "t_ms": 1781659157365,
      "jump": 0.05,
      "pre": 0.635,
      "p_entry": 0.815,
      "p_exit": 0.815,
      "reverted_pp": -0.0,
      "pnl_pp": -0.5,
      "surprise": 0.079,
      "gain_prior": 0.635,
      "surprising": false
    },
    {
      "t_ms": 1781662983399,
      "jump": 0.05,
      "pre": 0.835,
      "p_entry": 0.975,
      "p_exit": 0.975,
      "reverted_pp": -0.0,
      "pnl_pp": -0.5,
      "surprise": 0.06,
      "gain_prior": 0.835,
      "surprising": false
    }
  ],
  "summary": {
    "n": 3,
    "total_pnl_pp": 0.5,
    "hit_rate": 0.333,
    "mean_reverted_pp": 0.667,
    "mean_pnl_pp": 0.167,
    "per_trade_sharpe": null
  },
  "n_surprising": 0,
  "summary_surprising": {
    "n": 0,
    "total_pnl_pp": 0.0,
    "hit_rate": null,
    "mean_reverted_pp": null,
    "mean_pnl_pp": null,
    "per_trade_sharpe": null
  },
  "params": {
    "entry_s": 120,
    "exit_s": 360,
    "min_jump": 0.05,
    "cost_pp": 0.5,
    "surprise_underdog": 0.4
  }
}