{
  "match": "Brazil vs Haiti",
  "capture": "20260619T235702Z-brazil-vs-haiti",
  "home": "Brazil",
  "away": "Haiti",
  "pregame": [
    0.8808,
    0.1009,
    0.0183
  ],
  "lambdas": [
    2.75,
    0.3
  ],
  "final": [
    3,
    0
  ],
  "goal_source": "shock-inferred (MISMATCH (1, 0) vs final (3, 0))",
  "score_reconstruction_ok": false,
  "n_goals": 1,
  "goals": [
    {
      "minute": 25.4,
      "team": "Brazil",
      "score": "1-0",
      "model_home_before": 0.8103,
      "model_home_after": 0.9679,
      "model_jump": 0.1576,
      "mkt_home_pre": 0.865,
      "mkt_home_settle": 0.935,
      "mkt_jump": 0.07,
      "overshoot": -0.0876,
      "revert_60s": 0.01
    }
  ],
  "model_home_line": [
    [
      0,
      0.885
    ],
    [
      1,
      0.883
    ],
    [
      2,
      0.881
    ],
    [
      3,
      0.878
    ],
    [
      4,
      0.876
    ],
    [
      5,
      0.874
    ],
    [
      6,
      0.871
    ],
    [
      7,
      0.869
    ],
    [
      8,
      0.866
    ],
    [
      9,
      0.864
    ],
    [
      10,
      0.861
    ],
    [
      11,
      0.858
    ],
    [
      12,
      0.855
    ],
    [
      13,
      0.852
    ],
    [
      14,
      0.849
    ],
    [
      15,
      0.846
    ],
    [
      16,
      0.843
    ],
    [
      17,
      0.84
    ],
    [
      18,
      0.837
    ],
    [
      19,
      0.834
    ],
    [
      20,
      0.83
    ],
    [
      21,
      0.827
    ],
    [
      22,
      0.823
    ],
    [
      23,
      0.819
    ],
    [
      24,
      0.816
    ],
    [
      25,
      0.812
    ],
    [
      26,
      0.968
    ],
    [
      27,
      0.967
    ],
    [
      28,
      0.967
    ],
    [
      29,
      0.967
    ],
    [
      30,
      0.966
    ],
    [
      31,
      0.966
    ],
    [
      32,
      0.966
    ],
    [
      33,
      0.965
    ],
    [
      34,
      0.965
    ],
    [
      35,
      0.965
    ],
    [
      36,
      0.964
    ],
    [
      37,
      0.964
    ],
    [
      38,
      0.964
    ],
    [
      39,
      0.963
    ],
    [
      40,
      0.963
    ],
    [
      41,
      0.963
    ],
    [
      42,
      0.962
    ],
    [
      43,
      0.962
    ],
    [
      44,
      0.962
    ],
    [
      45,
      0.962
    ],
    [
      46,
      0.961
    ],
    [
      47,
      0.961
    ],
    [
      48,
      0.961
    ],
    [
      49,
      0.961
    ],
    [
      50,
      0.961
    ],
    [
      51,
      0.96
    ],
    [
      52,
      0.96
    ],
    [
      53,
      0.96
    ],
    [
      54,
      0.96
    ],
    [
      55,
      0.96
    ],
    [
      56,
      0.96
    ],
    [
      57,
      0.96
    ],
    [
      58,
      0.96
    ],
    [
      59,
      0.96
    ],
    [
      60,
      0.96
    ],
    [
      61,
      0.96
    ],
    [
      62,
      0.96
    ],
    [
      63,
      0.96
    ],
    [
      64,
      0.961
    ],
    [
      65,
      0.961
    ],
    [
      66,
      0.961
    ],
    [
      67,
      0.962
    ],
    [
      68,
      0.962
    ],
    [
      69,
      0.962
    ],
    [
      70,
      0.963
    ],
    [
      71,
      0.964
    ],
    [
      72,
      0.964
    ],
    [
      73,
      0.965
    ],
    [
      74,
      0.966
    ],
    [
      75,
      0.967
    ],
    [
      76,
      0.968
    ],
    [
      77,
      0.969
    ],
    [
      78,
      0.97
    ],
    [
      79,
      0.971
    ],
    [
      80,
      0.973
    ],
    [
      81,
      0.974
    ],
    [
      82,
      0.976
    ],
    [
      83,
      0.977
    ],
    [
      84,
      0.979
    ],
    [
      85,
      0.981
    ],
    [
      86,
      0.983
    ],
    [
      87,
      0.986
    ],
    [
      88,
      0.988
    ],
    [
      89,
      0.991
    ],
    [
      90,
      0.994
    ],
    [
      91,
      0.997
    ],
    [
      92,
      1.0
    ]
  ]
}