{
  "match": "Mexico vs South Korea",
  "capture": "20260619T002622Z-mexico-vs-south-korea",
  "home": "Mexico",
  "away": "South Korea",
  "pregame": [
    0.5708,
    0.2301,
    0.1991
  ],
  "lambdas": [
    1.8,
    0.95
  ],
  "final": [
    1,
    0
  ],
  "goal_source": "shock-inferred (MISMATCH (2, 0) vs final (1, 0))",
  "score_reconstruction_ok": false,
  "n_goals": 2,
  "goals": [
    {
      "minute": 54.7,
      "team": "Mexico",
      "score": "1-0",
      "model_home_before": 0.4024,
      "model_home_after": 0.8234,
      "model_jump": 0.421,
      "mkt_home_pre": 0.355,
      "mkt_home_settle": 0.755,
      "mkt_jump": 0.4,
      "overshoot": -0.021,
      "revert_60s": -0.02
    },
    {
      "minute": 99.8,
      "team": "Mexico",
      "score": "2-0",
      "model_home_before": 1.0,
      "model_home_after": 1.0,
      "model_jump": 0.0,
      "mkt_home_pre": 0.945,
      "mkt_home_settle": 0.965,
      "mkt_jump": 0.02,
      "overshoot": 0.02,
      "revert_60s": 0.025
    }
  ],
  "model_home_line": [
    [
      0,
      0.578
    ],
    [
      1,
      0.576
    ],
    [
      2,
      0.574
    ],
    [
      3,
      0.572
    ],
    [
      4,
      0.57
    ],
    [
      5,
      0.568
    ],
    [
      6,
      0.565
    ],
    [
      7,
      0.563
    ],
    [
      8,
      0.561
    ],
    [
      9,
      0.559
    ],
    [
      10,
      0.557
    ],
    [
      11,
      0.555
    ],
    [
      12,
      0.552
    ],
    [
      13,
      0.55
    ],
    [
      14,
      0.548
    ],
    [
      15,
      0.545
    ],
    [
      16,
      0.543
    ],
    [
      17,
      0.54
    ],
    [
      18,
      0.538
    ],
    [
      19,
      0.535
    ],
    [
      20,
      0.533
    ],
    [
      21,
      0.53
    ],
    [
      22,
      0.527
    ],
    [
      23,
      0.525
    ],
    [
      24,
      0.522
    ],
    [
      25,
      0.519
    ],
    [
      26,
      0.516
    ],
    [
      27,
      0.513
    ],
    [
      28,
      0.51
    ],
    [
      29,
      0.507
    ],
    [
      30,
      0.504
    ],
    [
      31,
      0.501
    ],
    [
      32,
      0.498
    ],
    [
      33,
      0.495
    ],
    [
      34,
      0.491
    ],
    [
      35,
      0.488
    ],
    [
      36,
      0.485
    ],
    [
      37,
      0.481
    ],
    [
      38,
      0.477
    ],
    [
      39,
      0.474
    ],
    [
      40,
      0.47
    ],
    [
      41,
      0.466
    ],
    [
      42,
      0.462
    ],
    [
      43,
      0.458
    ],
    [
      44,
      0.454
    ],
    [
      45,
      0.45
    ],
    [
      46,
      0.445
    ],
    [
      47,
      0.441
    ],
    [
      48,
      0.436
    ],
    [
      49,
      0.432
    ],
    [
      50,
      0.427
    ],
    [
      51,
      0.422
    ],
    [
      52,
      0.417
    ],
    [
      53,
      0.412
    ],
    [
      54,
      0.406
    ],
    [
      55,
      0.824
    ],
    [
      56,
      0.826
    ],
    [
      57,
      0.827
    ],
    [
      58,
      0.829
    ],
    [
      59,
      0.831
    ],
    [
      60,
      0.833
    ],
    [
      61,
      0.835
    ],
    [
      62,
      0.837
    ],
    [
      63,
      0.84
    ],
    [
      64,
      0.842
    ],
    [
      65,
      0.845
    ],
    [
      66,
      0.847
    ],
    [
      67,
      0.85
    ],
    [
      68,
      0.853
    ],
    [
      69,
      0.856
    ],
    [
      70,
      0.86
    ],
    [
      71,
      0.863
    ],
    [
      72,
      0.867
    ],
    [
      73,
      0.871
    ],
    [
      74,
      0.875
    ],
    [
      75,
      0.88
    ],
    [
      76,
      0.884
    ],
    [
      77,
      0.889
    ],
    [
      78,
      0.894
    ],
    [
      79,
      0.899
    ],
    [
      80,
      0.905
    ],
    [
      81,
      0.911
    ],
    [
      82,
      0.917
    ],
    [
      83,
      0.924
    ],
    [
      84,
      0.931
    ],
    [
      85,
      0.938
    ],
    [
      86,
      0.945
    ],
    [
      87,
      0.953
    ],
    [
      88,
      0.962
    ],
    [
      89,
      0.971
    ],
    [
      90,
      0.98
    ],
    [
      91,
      0.99
    ],
    [
      92,
      1.0
    ]
  ]
}